sendalert/__init__.py
sendalert/core.py
sendalert-0.2.0.dist-info/LICENSE
sendalert-0.2.0.dist-info/METADATA
sendalert-0.2.0.dist-info/WHEEL
sendalert-0.2.0.dist-info/top_level.txt
sendalert-0.2.0.dist-info/RECORD
