Metadata-Version: 2.1
Name: sendalert
Version: 0.2.0
Summary: A simple Python package for sending alerts using SendAlert.io
Home-page: https://github.com/philz1337x/sendalert-python
Author: philz1337x
Author-email: python@okasi.de
Classifier: Programming Language :: Python :: 3
Classifier: License :: OSI Approved :: MIT License
Classifier: Operating System :: OS Independent
Requires-Python: >=3.6
License-File: LICENSE
Requires-Dist: requests
